croncaster/__init__.py
croncaster/__main__.py
croncaster/config.py
croncaster/state.py
croncaster/tools.py
croncaster-0.2.0.dist-info/LICENSE
croncaster-0.2.0.dist-info/WHEEL
croncaster-0.2.0.dist-info/METADATA
croncaster-0.2.0.dist-info/RECORD
